winrt_microsoft_ui_xaml/__init__.py
winrt_microsoft_ui_xaml/cppwinrt/winrt/Microsoft.UI.Xaml.Automation.Peers.h
winrt_microsoft_ui_xaml/cppwinrt/winrt/Microsoft.UI.Xaml.Controls.AnimatedVisuals.h
winrt_microsoft_ui_xaml/cppwinrt/winrt/Microsoft.UI.Xaml.Controls.Primitives.h
winrt_microsoft_ui_xaml/cppwinrt/winrt/Microsoft.UI.Xaml.Controls.h
winrt_microsoft_ui_xaml/cppwinrt/winrt/Microsoft.UI.Xaml.Media.h
winrt_microsoft_ui_xaml/cppwinrt/winrt/Microsoft.UI.Xaml.XamlTypeInfo.h
winrt_microsoft_ui_xaml/cppwinrt/winrt/impl/Microsoft.UI.Xaml.Automation.Peers.0.h
winrt_microsoft_ui_xaml/cppwinrt/winrt/impl/Microsoft.UI.Xaml.Automation.Peers.1.h
winrt_microsoft_ui_xaml/cppwinrt/winrt/impl/Microsoft.UI.Xaml.Automation.Peers.2.h
winrt_microsoft_ui_xaml/cppwinrt/winrt/impl/Microsoft.UI.Xaml.Controls.0.h
winrt_microsoft_ui_xaml/cppwinrt/winrt/impl/Microsoft.UI.Xaml.Controls.1.h
winrt_microsoft_ui_xaml/cppwinrt/winrt/impl/Microsoft.UI.Xaml.Controls.2.h
winrt_microsoft_ui_xaml/cppwinrt/winrt/impl/Microsoft.UI.Xaml.Controls.AnimatedVisuals.0.h
winrt_microsoft_ui_xaml/cppwinrt/winrt/impl/Microsoft.UI.Xaml.Controls.AnimatedVisuals.1.h
winrt_microsoft_ui_xaml/cppwinrt/winrt/impl/Microsoft.UI.Xaml.Controls.AnimatedVisuals.2.h
winrt_microsoft_ui_xaml/cppwinrt/winrt/impl/Microsoft.UI.Xaml.Controls.Primitives.0.h
winrt_microsoft_ui_xaml/cppwinrt/winrt/impl/Microsoft.UI.Xaml.Controls.Primitives.1.h
winrt_microsoft_ui_xaml/cppwinrt/winrt/impl/Microsoft.UI.Xaml.Controls.Primitives.2.h
winrt_microsoft_ui_xaml/cppwinrt/winrt/impl/Microsoft.UI.Xaml.Media.0.h
winrt_microsoft_ui_xaml/cppwinrt/winrt/impl/Microsoft.UI.Xaml.Media.1.h
winrt_microsoft_ui_xaml/cppwinrt/winrt/impl/Microsoft.UI.Xaml.Media.2.h
winrt_microsoft_ui_xaml/cppwinrt/winrt/impl/Microsoft.UI.Xaml.XamlTypeInfo.0.h
winrt_microsoft_ui_xaml/cppwinrt/winrt/impl/Microsoft.UI.Xaml.XamlTypeInfo.1.h
winrt_microsoft_ui_xaml/cppwinrt/winrt/impl/Microsoft.UI.Xaml.XamlTypeInfo.2.h
winrt_microsoft_ui_xaml-3.2.1.dist-info/METADATA
winrt_microsoft_ui_xaml-3.2.1.dist-info/WHEEL
winrt_microsoft_ui_xaml-3.2.1.dist-info/top_level.txt
winrt_microsoft_ui_xaml-3.2.1.dist-info/RECORD
