Metadata-Version: 2.4
Name: winrt-Microsoft.UI.Xaml
Version: 3.2.1
Summary: Windows Runtime SDK for Python header files
License-Expression: MIT
Project-URL: Documentation, https://pywinrt.readthedocs.io
Project-URL: Repository, https://github.com/pywinrt/pywinrt
Project-URL: Changelog, https://github.com/pywinrt/pywinrt/blob/main/CHANGELOG.md
Classifier: Operating System :: Microsoft :: Windows
Classifier: Programming Language :: Python :: 3
Classifier: Programming Language :: Python :: Implementation :: CPython
Classifier: Intended Audience :: Developers
Requires-Python: >=3.9
Requires-Dist: winrt-sdk~=3.2.1.0
Requires-Dist: webview2-Microsoft.Web.WebView2.Core~=3.2.1.0
